{
  "project_info": {
    "project_number": "586166674163",
    "firebase_url": "https://beacon-detector.firebaseio.com",
    "project_id": "beacon-detector",
    "storage_bucket": "beacon-detector.appspot.com"
  },
  "client": [
    {
      "client_info": {
        "mobilesdk_app_id": "1:586166674163:android:44098d00c0e3ad96",
        "android_client_info": {
          "package_name": "beacondetector.emulk.it.beacondetector"
        }
      },
      "oauth_client": [
        {
          "client_id": "586166674163-briutucrtm101he9icoc978984lcteve.apps.googleusercontent.com",
          "client_type": 3
        },
        {
          "client_id": "586166674163-tpl27b6lj434vneu49h13hc5am692v54.apps.googleusercontent.com",
          "client_type": 3
        }
      ],
      "api_key": [
        {
          "current_key": "AIzaSyAIEqQaCEXAm6P0PRqUp-Wh3oOaH3DwZA8"
        }
      ],
      "services": {
        "analytics_service": {
          "status": 2,
          "analytics_property": {
            "tracking_id": "UA-79934603-1"
          }
        },
        "appinvite_service": {
          "status": 1,
          "other_platform_oauth_client": []
        },
        "ads_service": {
          "status": 2
        }
      }
    }
  ],
  "configuration_version": "1"
}